anasymod
tests
