Metadata-Version: 2.1
Name: anasymod
Version: 0.2.9
Summary: Tool for running mixed-signal emulations on FPGAs
Home-page: https://github.com/sgherbst/anasymod
Author: Gabriel Rutsch, Steven Herbst, Shivani Saravanan
Author-email: gabriel.rutsch@infineon.com
License: BSD 3-Clause "New" or "Revised" License
Download-URL: https://github.com/sgherbst/anasymod/archive/v0.2.9.tar.gz
Keywords: analog,mixed-signal,mixed signal,vivado,xcelium,iverilog,icarus-verilog,icarus verilog,generator,verilog,system-verilog,system verilog,emulation,fpga
Platform: UNKNOWN
Classifier: Development Status :: 3 - Alpha
Classifier: Intended Audience :: Developers
Classifier: Topic :: Scientific/Engineering :: Electronic Design Automation (EDA)
Classifier: License :: OSI Approved :: BSD License
Classifier: Programming Language :: Python :: 3.7
Requires-Python: >=3.7
